{
    "AX": {
        "error": 0.016340190633654366,
        "error_type": "SEM",
        "filter_outliers_dict": {
            "filter_outliers": true,
            "iterations": 1,
            "std_devs": 3,
            "use_iqr_filtering": false,
            "use_standard_deviation_filtering": false
        },
        "fit": "Average",
        "fn": 20,
        "include_baseline_error": true,
        "n": 20,
        "outlier_excluded": [],
        "reviewed": true,
        "user_excluded": [],
        "value": 0.00665170403663069
    },
    "CDD": {
        "error": 1.678466540622186e-05,
        "error_type": "SEM",
        "filter_outliers_dict": {
            "filter_outliers": true,
            "iterations": 1,
            "std_devs": 10
        },
        "fit": "average",
        "value": 2.30085921920262e-05
    },
    "H1": {
        "error": 0.008775533851620127,
        "error_type": "SEM",
        "filter_outliers_dict": {
            "filter_outliers": true,
            "iterations": 1,
            "std_devs": 3,
            "use_iqr_filtering": false,
            "use_standard_deviation_filtering": false
        },
        "fit": "Average",
        "fn": 20,
        "include_baseline_error": true,
        "n": 20,
        "outlier_excluded": [],
        "reviewed": true,
        "user_excluded": [],
        "value": 0.019705780828371645
    },
    "H2": {
        "error": 0.05951693713467886,
        "error_type": "SEM",
        "filter_outliers_dict": {
            "filter_outliers": true,
            "iterations": 1,
            "std_devs": 2
        },
        "fit": "average",
        "value": -0.5772925106138473
    },
    "L1": {
        "error": 0.0043771168429390505,
        "error_type": "SEM",
        "filter_outliers_dict": {
            "filter_outliers": true,
            "iterations": 1,
            "std_devs": 3,
            "use_iqr_filtering": false,
            "use_standard_deviation_filtering": false
        },
        "fit": "Average",
        "fn": 20,
        "include_baseline_error": true,
        "n": 20,
        "outlier_excluded": [],
        "reviewed": true,
        "user_excluded": [],
        "value": 0.02053221032838337
    },
    "L2": {
        "error": 0.005920816824697578,
        "error_type": "SEM",
        "filter_outliers_dict": {
            "filter_outliers": true,
            "iterations": 1,
            "std_devs": 2
        },
        "fit": "average",
        "value": -0.04394340857354191
    }
}