{
    "AX": {
        "error": 0.00492178832547571,
        "error_type": "SEM",
        "filter_outliers_dict": {
            "filter_outliers": true,
            "iterations": 1,
            "std_devs": 3,
            "use_iqr_filtering": false,
            "use_standard_deviation_filtering": false
        },
        "fit": "Average",
        "fn": 129,
        "include_baseline_error": true,
        "n": 129,
        "outlier_excluded": [],
        "reviewed": true,
        "user_excluded": [],
        "value": -0.0962240867670481
    },
    "CDD": {
        "error": 3.6084821668229566e-06,
        "error_type": "SEM",
        "filter_outliers_dict": {
            "filter_outliers": true,
            "iterations": 1,
            "std_devs": 10,
            "use_iqr_filtering": false,
            "use_standard_deviation_filtering": false
        },
        "fit": "Average",
        "fn": 129,
        "include_baseline_error": true,
        "n": 129,
        "outlier_excluded": [],
        "reviewed": true,
        "user_excluded": [],
        "value": 1.1834667683326342e-05
    },
    "H1": {
        "error": 0.003753810593726716,
        "error_type": "SEM",
        "filter_outliers_dict": {
            "filter_outliers": true,
            "iterations": 1,
            "std_devs": 3,
            "use_iqr_filtering": false,
            "use_standard_deviation_filtering": false
        },
        "fit": "Average",
        "fn": 129,
        "include_baseline_error": true,
        "n": 129,
        "outlier_excluded": [],
        "reviewed": true,
        "user_excluded": [],
        "value": 0.005255400416934898
    },
    "H2": {
        "error": 0.0014984994478388994,
        "error_type": "SEM",
        "filter_outliers_dict": {
            "filter_outliers": true,
            "iterations": 1,
            "std_devs": 2
        },
        "fit": "average",
        "value": -0.0212946455043761
    },
    "L1": {
        "error": 0.002123624269903885,
        "error_type": "SEM",
        "filter_outliers_dict": {
            "filter_outliers": true,
            "iterations": 1,
            "std_devs": 3,
            "use_iqr_filtering": false,
            "use_standard_deviation_filtering": false
        },
        "fit": "Average",
        "fn": 128,
        "include_baseline_error": true,
        "n": 129,
        "outlier_excluded": [
            124
        ],
        "reviewed": true,
        "user_excluded": [],
        "value": 0.0187126130187778
    },
    "L2": {
        "error": 0.004662253998286021,
        "error_type": "SEM",
        "filter_outliers_dict": {
            "filter_outliers": true,
            "iterations": 1,
            "std_devs": 3,
            "use_iqr_filtering": false,
            "use_standard_deviation_filtering": false
        },
        "fit": "Average",
        "fn": 129,
        "include_baseline_error": true,
        "n": 129,
        "outlier_excluded": [],
        "reviewed": true,
        "user_excluded": [],
        "value": -0.06039478794151336
    }
}